uniquebible/README.md
uniquebible/RunNHide.vbs
uniquebible/UniqueBibleAppVersion.txt
uniquebible/__init__.py
uniquebible/activate_this.py
uniquebible/api-server.sh
uniquebible/config.py
uniquebible/createAudioBible.py
uniquebible/debug.py
uniquebible/docker_requirements.txt
uniquebible/download.py
uniquebible/file_manager.py
uniquebible/http-server.sh
uniquebible/install.sh
uniquebible/kill-api-server.sh
uniquebible/kill-http-server.sh
uniquebible/latest_changes.txt
uniquebible/main.py
uniquebible/note_command_hyperlink_example.uba
uniquebible/note_editor.uba
uniquebible/note_editor_key_combo.uba
uniquebible/package_name.txt
uniquebible/patches.txt
uniquebible/requirements.txt
uniquebible/set_macOS_icon.py
uniquebible/shortcut.py
uniquebible/text_editor.py
uniquebible/uba.py
uniquebible/uba_gnome-terminal.sh
uniquebible/update.py
uniquebible/audio/Readme.md
uniquebible/audio/create_playlist.py
uniquebible/db/AGBTSData.py
uniquebible/db/BibleDataConverter.py
uniquebible/db/BibleVectorDatabase.py
uniquebible/db/BiblesSqlite.py
uniquebible/db/BiblesSqlite_nogui.py
uniquebible/db/DevotionalSqlite.py
uniquebible/db/Highlight.py
uniquebible/db/IndexSqlite.py
uniquebible/db/JEPDData.py
uniquebible/db/JEPDSqlite.py
uniquebible/db/JournalSqlite.py
uniquebible/db/LiveFilterSqlite.py
uniquebible/db/NoteSqlite.py
uniquebible/db/StatisticsWordsSqlite.py
uniquebible/db/ToolsSqlite.py
uniquebible/db/UserRepoSqlite.py
uniquebible/gui/AlephMainWindow.py
uniquebible/gui/AppUpdateDialog.py
uniquebible/gui/BarChart.py
uniquebible/gui/BibleCollectionDialog.py
uniquebible/gui/BibleExplorer.py
uniquebible/gui/CentralWidget.py
uniquebible/gui/CheckableComboBox.py
uniquebible/gui/ClassicMainWindow.py
uniquebible/gui/ConfigFlagsWindow.py
uniquebible/gui/DisplayShortcutsWindow.py
uniquebible/gui/DownloadBibleMp3Dialog.py
uniquebible/gui/Downloader.py
uniquebible/gui/EditGuiLanguageFileDialog.py
uniquebible/gui/EnableIndividualPlugins.py
uniquebible/gui/FocusMainWindow.py
uniquebible-0.2.28.dist-info/LICENSE
uniquebible-0.2.28.dist-info/METADATA
uniquebible-0.2.28.dist-info/WHEEL
uniquebible-0.2.28.dist-info/entry_points.txt
uniquebible-0.2.28.dist-info/top_level.txt
uniquebible-0.2.28.dist-info/RECORD
