Metadata-Version: 2.1
Name: uniquebible
Version: 0.2.28
Summary: UniqueBible App is a cross-platform & offline bible application, integrated with high-quality resources and unique features. Developers: Eliran Wong and Oliver Tseng
Home-page: https://www.uniquebible.app/
Author: Eliran Wong
Author-email: support@biblemate.ai
License: GNU General Public License (GPL)
Project-URL: Source, https://github.com/eliranwong/UniqueBible
Project-URL: Tracker, https://github.com/eliranwong/UniqueBible/issues
Project-URL: Documentation, https://github.com/eliranwong/UniqueBible/wiki
Project-URL: Funding, https://www.paypal.me/MarvelBible
Keywords: bible scripture na28 bsha hebrew greek ai marvelbible biblebento uba uniquebible
Classifier: Development Status :: 5 - Production/Stable
Classifier: Intended Audience :: End Users/Desktop
Classifier: Topic :: Utilities
Classifier: Topic :: Scientific/Engineering :: Artificial Intelligence
Classifier: Topic :: Software Development :: Build Tools
Classifier: License :: OSI Approved :: GNU General Public License v3 or later (GPLv3+)
Classifier: Programming Language :: Python :: 3.8
Classifier: Programming Language :: Python :: 3.9
Classifier: Programming Language :: Python :: 3.10
Classifier: Programming Language :: Python :: 3.11
Classifier: Programming Language :: Python :: 3.12
Requires-Python: >=3.8, <3.13
License-File: LICENSE
Requires-Dist: apsw
Requires-Dist: babel
Requires-Dist: gdown
Requires-Dist: groq
Requires-Dist: haversine
Requires-Dist: markdown
Requires-Dist: mistralai
Requires-Dist: openai
Requires-Dist: opencc-python-reimplemented
Requires-Dist: packaging
Requires-Dist: prompt-toolkit
Requires-Dist: requests
Requires-Dist: uniquebible-maps-1 ==0.0.3
Requires-Dist: uniquebible-maps-2 ==0.0.3
Requires-Dist: uniquebible-maps-3 ==0.0.3
Requires-Dist: uniquebible-maps-4 ==0.0.3
Requires-Dist: uniquebible-maps-5 ==0.0.3
Requires-Dist: xonsh[full]
Provides-Extra: gui
Requires-Dist: PySide6 ; extra == 'gui'
